[
    {
        "fold": "1",
        "fp": {
            "EF1": 25.4705840529779,
            "ROC": 0.8811986847533559
        },
        "prop": {
            "EF1": 17.7990654857918,
            "ROC": 0.832845860001029
        }
    },
    {
        "fold": "2",
        "fp": {
            "EF1": 28.11812784389248,
            "ROC": 0.923526989647443
        },
        "prop": {
            "EF1": 13.501135479497325,
            "ROC": 0.8196964266927607
        }
    },
    {
        "fold": "3",
        "fp": {
            "EF1": 24.63965871334737,
            "ROC": 0.9074334710519244
        },
        "prop": {
            "EF1": 18.110039439804943,
            "ROC": 0.8344955979912614
        }
    },
    {
        "fp": {
            "EF1": 26.07612353673925,
            "ROC": 0.9040530484842412
        },
        "prop": {
            "EF1": 16.470080135031356,
            "ROC": 0.8290126282283503
        }
    }
]